{
  "family_id": "stat_score_cha",
  "display_name": "Ability Score: Charisma",
  "position": "suffix",
  "slot": "all",
  "affix_id": "score_cha",
  "element": null,
  "mechanic": "add_ability_score",
  "stat": "CHA",
  "tiers": {
    "common":    ["the Herald", "Charm", "the Speaker"],
    "uncommon":  ["the Noble", "Authority", "the Diplomat"],
    "rare":      ["the Sovereign", "Majesty", "the Commander"],
    "epic":      ["the Idol", "Eminence", "the Exalted"],
    "legendary": ["the Paragon", "Apotheosis", "the Undeniable"]
  }
}
